pyjs_code_runner/__init__.py
pyjs_code_runner/constants.py
pyjs_code_runner/get_cache_dir.py
pyjs_code_runner/get_file_filter.py
pyjs_code_runner/run.py
pyjs_code_runner/version.py
pyjs_code_runner/work_dir_context.py
pyjs_code_runner/backend/__init__.py
pyjs_code_runner/backend/backend.py
pyjs_code_runner/backend/backend_base.py
pyjs_code_runner/backend/browser_main/__init__.py
pyjs_code_runner/backend/browser_main/browser_main.py
pyjs_code_runner/backend/browser_main/server.py
pyjs_code_runner/backend/browser_worker/__init__.py
pyjs_code_runner/backend/browser_worker/browser_worker.py
pyjs_code_runner/backend/node/__init__.py
pyjs_code_runner/backend/node/node.py
pyjs_code_runner/backend/node/node_main.js
pyjs_code_runner/cli/__init__.py
pyjs_code_runner/cli/app.py
pyjs_code_runner/cli/err.py
pyjs_code_runner/cli/main.py
pyjs_code_runner/cli/run.py
pyjs_code_runner/cli/utils.py
pyjs_code_runner/cli/version.py
pyjs_code_runner/html/__init__.py
pyjs_code_runner/html/browser_main.html
pyjs_code_runner/html/browser_worker.html
pyjs_code_runner/js/__init__.py
pyjs_code_runner/js/utils.js
pyjs_code_runner/js/worker.js
pyjs_code_runner-3.0.0.dist-info/METADATA
pyjs_code_runner-3.0.0.dist-info/WHEEL
pyjs_code_runner-3.0.0.dist-info/entry_points.txt
pyjs_code_runner-3.0.0.dist-info/licenses/LICENSE
pyjs_code_runner-3.0.0.dist-info/RECORD
