Metadata-Version: 2.3
Name: pyjs-code-runner
Version: 3.0.0
Summary: A driver to run wasm code from an emscripten-forge coda env like normal python code
Project-URL: Homepage, https://github.com/emscripten-forge/pyjs-code-runner
Author-email: Thorsten Beier <derthorstenbeier@gmail.com>
License: Copyright (c) 2022 Dr. Thorsten Beier
License-File: LICENSE
Keywords: pyjs_code_runner
Classifier: Intended Audience :: Developers
Classifier: Natural Language :: English
Classifier: Programming Language :: Python :: 3.10
Classifier: Programming Language :: Python :: 3.11
Requires-Dist: appdirs
Requires-Dist: empack>=3.0.0
Requires-Dist: playwright
Requires-Dist: rich
Requires-Dist: typer
